[
  {
    "numero_procedimento": "N/A",
    "entidade": "Anúncio de procedimento  n.º 25473/2025  -  Diário da República n.º 187/2025, Série II de 2025-09-29",
    "link": "https://diariodarepublica.pt/dr/detalhe/contrato-publico/25473-936971409"
  },
  {
    "numero_procedimento": "N/A",
    "entidade": "Anúncio de procedimento  n.º 25476/2025  -  Diário da República n.º 187/2025, Série II de 2025-09-29",
    "link": "https://diariodarepublica.pt/dr/detalhe/contrato-publico/25476-936971410"
  },
  {
    "numero_procedimento": "N/A",
    "entidade": "Anúncio de procedimento  n.º 25477/2025  -  Diário da República n.º 187/2025, Série II de 2025-09-29",
    "link": "https://diariodarepublica.pt/dr/detalhe/contrato-publico/25477-936971411"
  },
  {
    "numero_procedimento": "N/A",
    "entidade": "Anúncio de procedimento  n.º 25478/2025  -  Diário da República n.º 187/2025, Série II de 2025-09-29",
    "link": "https://diariodarepublica.pt/dr/detalhe/contrato-publico/25478-936971412"
  },
  {
    "numero_procedimento": "N/A",
    "entidade": "Anúncio de procedimento  n.º 25479/2025  -  Diário da República n.º 187/2025, Série II de 2025-09-29",
    "link": "https://diariodarepublica.pt/dr/detalhe/contrato-publico/25479-936971413"
  },
  {
    "numero_procedimento": "N/A",
    "entidade": "Anúncio de procedimento  n.º 25480/2025  -  Diário da República n.º 187/2025, Série II de 2025-09-29",
    "link": "https://diariodarepublica.pt/dr/detalhe/contrato-publico/25480-936971414"
  },
  {
    "numero_procedimento": "N/A",
    "entidade": "Anúncio de procedimento  n.º 25481/2025  -  Diário da República n.º 187/2025, Série II de 2025-09-29",
    "link": "https://diariodarepublica.pt/dr/detalhe/contrato-publico/25481-936971415"
  },
  {
    "numero_procedimento": "N/A",
    "entidade": "Anúncio de procedimento  n.º 25483/2025  -  Diário da República n.º 187/2025, Série II de 2025-09-29",
    "link": "https://diariodarepublica.pt/dr/detalhe/contrato-publico/25483-936971419"
  },
  {
    "numero_procedimento": "N/A",
    "entidade": "Anúncio de procedimento  n.º 25484/2025  -  Diário da República n.º 187/2025, Série II de 2025-09-29",
    "link": "https://diariodarepublica.pt/dr/detalhe/contrato-publico/25484-936971420"
  },
  {
    "numero_procedimento": "N/A",
    "entidade": "Anúncio de procedimento  n.º 25485/2025  -  Diário da República n.º 187/2025, Série II de 2025-09-29",
    "link": "https://diariodarepublica.pt/dr/detalhe/contrato-publico/25485-936971421"
  },
  {
    "numero_procedimento": "N/A",
    "entidade": "Anúncio de procedimento  n.º 25486/2025  -  Diário da República n.º 187/2025, Série II de 2025-09-29",
    "link": "https://diariodarepublica.pt/dr/detalhe/contrato-publico/25486-936971422"
  },
  {
    "numero_procedimento": "N/A",
    "entidade": "Anúncio de procedimento  n.º 25487/2025  -  Diário da República n.º 187/2025, Série II de 2025-09-29",
    "link": "https://diariodarepublica.pt/dr/detalhe/contrato-publico/25487-936971423"
  },
  {
    "numero_procedimento": "N/A",
    "entidade": "Anúncio de procedimento  n.º 25491/2025  -  Diário da República n.º 187/2025, Série II de 2025-09-29",
    "link": "https://diariodarepublica.pt/dr/detalhe/contrato-publico/25491-936971424"
  },
  {
    "numero_procedimento": "N/A",
    "entidade": "Anúncio de procedimento  n.º 25493/2025  -  Diário da República n.º 187/2025, Série II de 2025-09-29",
    "link": "https://diariodarepublica.pt/dr/detalhe/contrato-publico/25493-936971425"
  },
  {
    "numero_procedimento": "N/A",
    "entidade": "Anúncio de procedimento  n.º 25497/2025  -  Diário da República n.º 187/2025, Série II de 2025-09-29",
    "link": "https://diariodarepublica.pt/dr/detalhe/contrato-publico/25497-936971426"
  },
  {
    "numero_procedimento": "N/A",
    "entidade": "Anúncio de procedimento  n.º 25499/2025  -  Diário da República n.º 187/2025, Série II de 2025-09-29",
    "link": "https://diariodarepublica.pt/dr/detalhe/contrato-publico/25499-936971427"
  },
  {
    "numero_procedimento": "N/A",
    "entidade": "Anúncio de procedimento  n.º 25500/2025  -  Diário da República n.º 187/2025, Série II de 2025-09-29",
    "link": "https://diariodarepublica.pt/dr/detalhe/contrato-publico/25500-936971428"
  },
  {
    "numero_procedimento": "N/A",
    "entidade": "Anúncio de procedimento  n.º 25501/2025  -  Diário da República n.º 187/2025, Série II de 2025-09-29",
    "link": "https://diariodarepublica.pt/dr/detalhe/contrato-publico/25501-936971429"
  },
  {
    "numero_procedimento": "N/A",
    "entidade": "Anúncio de procedimento  n.º 25504/2025  -  Diário da República n.º 187/2025, Série II de 2025-09-29",
    "link": "https://diariodarepublica.pt/dr/detalhe/contrato-publico/25504-936971430"
  },
  {
    "numero_procedimento": "N/A",
    "entidade": "Anúncio de procedimento  n.º 25508/2025  -  Diário da República n.º 187/2025, Série II de 2025-09-29",
    "link": "https://diariodarepublica.pt/dr/detalhe/contrato-publico/25508-936971431"
  },
  {
    "numero_procedimento": "N/A",
    "entidade": "Anúncio de procedimento  n.º 25509/2025  -  Diário da República n.º 187/2025, Série II de 2025-09-29",
    "link": "https://diariodarepublica.pt/dr/detalhe/contrato-publico/25509-936971432"
  },
  {
    "numero_procedimento": "N/A",
    "entidade": "Anúncio de procedimento  n.º 25511/2025  -  Diário da República n.º 187/2025, Série II de 2025-09-29",
    "link": "https://diariodarepublica.pt/dr/detalhe/contrato-publico/25511-936971433"
  },
  {
    "numero_procedimento": "N/A",
    "entidade": "Anúncio de procedimento  n.º 25513/2025  -  Diário da República n.º 187/2025, Série II de 2025-09-29",
    "link": "https://diariodarepublica.pt/dr/detalhe/contrato-publico/25513-936971434"
  },
  {
    "numero_procedimento": "N/A",
    "entidade": "Anúncio de procedimento  n.º 25514/2025  -  Diário da República n.º 187/2025, Série II de 2025-09-29",
    "link": "https://diariodarepublica.pt/dr/detalhe/contrato-publico/25514-936971435"
  },
  {
    "numero_procedimento": "N/A",
    "entidade": "Anúncio de procedimento  n.º 25517/2025  -  Diário da República n.º 187/2025, Série II de 2025-09-29",
    "link": "https://diariodarepublica.pt/dr/detalhe/contrato-publico/25517-936971436"
  },
  {
    "numero_procedimento": "N/A",
    "entidade": "Anúncio de procedimento  n.º 25518/2025  -  Diário da República n.º 187/2025, Série II de 2025-09-29",
    "link": "https://diariodarepublica.pt/dr/detalhe/contrato-publico/25518-936971437"
  },
  {
    "numero_procedimento": "N/A",
    "entidade": "Anúncio de procedimento  n.º 25520/2025  -  Diário da República n.º 187/2025, Série II de 2025-09-29",
    "link": "https://diariodarepublica.pt/dr/detalhe/contrato-publico/25520-936971438"
  },
  {
    "numero_procedimento": "N/A",
    "entidade": "Anúncio de procedimento  n.º 25522/2025  -  Diário da República n.º 187/2025, Série II de 2025-09-29",
    "link": "https://diariodarepublica.pt/dr/detalhe/contrato-publico/25522-936971439"
  },
  {
    "numero_procedimento": "N/A",
    "entidade": "Anúncio de procedimento  n.º 25524/2025  -  Diário da República n.º 187/2025, Série II de 2025-09-29",
    "link": "https://diariodarepublica.pt/dr/detalhe/contrato-publico/25524-936971440"
  },
  {
    "numero_procedimento": "N/A",
    "entidade": "Anúncio de procedimento  n.º 25525/2025  -  Diário da República n.º 187/2025, Série II de 2025-09-29",
    "link": "https://diariodarepublica.pt/dr/detalhe/contrato-publico/25525-936971441"
  },
  {
    "numero_procedimento": "N/A",
    "entidade": "Anúncio de procedimento  n.º 25527/2025  -  Diário da República n.º 187/2025, Série II de 2025-09-29",
    "link": "https://diariodarepublica.pt/dr/detalhe/contrato-publico/25527-936971442"
  },
  {
    "numero_procedimento": "N/A",
    "entidade": "Anúncio de procedimento  n.º 25529/2025  -  Diário da República n.º 187/2025, Série II de 2025-09-29",
    "link": "https://diariodarepublica.pt/dr/detalhe/contrato-publico/25529-936971443"
  },
  {
    "numero_procedimento": "N/A",
    "entidade": "Anúncio de procedimento  n.º 25532/2025  -  Diário da República n.º 187/2025, Série II de 2025-09-29",
    "link": "https://diariodarepublica.pt/dr/detalhe/contrato-publico/25532-936971444"
  },
  {
    "numero_procedimento": "N/A",
    "entidade": "Anúncio de procedimento  n.º 25536/2025  -  Diário da República n.º 187/2025, Série II de 2025-09-29",
    "link": "https://diariodarepublica.pt/dr/detalhe/contrato-publico/25536-936971445"
  },
  {
    "numero_procedimento": "N/A",
    "entidade": "Anúncio de procedimento  n.º 25538/2025  -  Diário da República n.º 187/2025, Série II de 2025-09-29",
    "link": "https://diariodarepublica.pt/dr/detalhe/contrato-publico/25538-936971446"
  },
  {
    "numero_procedimento": "N/A",
    "entidade": "Anúncio de procedimento  n.º 25539/2025  -  Diário da República n.º 187/2025, Série II de 2025-09-29",
    "link": "https://diariodarepublica.pt/dr/detalhe/contrato-publico/25539-936971447"
  },
  {
    "numero_procedimento": "N/A",
    "entidade": "Anúncio de procedimento  n.º 25541/2025  -  Diário da República n.º 187/2025, Série II de 2025-09-29",
    "link": "https://diariodarepublica.pt/dr/detalhe/contrato-publico/25541-936971448"
  },
  {
    "numero_procedimento": "N/A",
    "entidade": "Anúncio de procedimento  n.º 25546/2025  -  Diário da República n.º 187/2025, Série II de 2025-09-29",
    "link": "https://diariodarepublica.pt/dr/detalhe/contrato-publico/25546-936971449"
  },
  {
    "numero_procedimento": "N/A",
    "entidade": "Anúncio de procedimento  n.º 25548/2025  -  Diário da República n.º 187/2025, Série II de 2025-09-29",
    "link": "https://diariodarepublica.pt/dr/detalhe/contrato-publico/25548-936971450"
  },
  {
    "numero_procedimento": "N/A",
    "entidade": "Anúncio de procedimento  n.º 25549/2025  -  Diário da República n.º 187/2025, Série II de 2025-09-29",
    "link": "https://diariodarepublica.pt/dr/detalhe/contrato-publico/25549-936971451"
  },
  {
    "numero_procedimento": "N/A",
    "entidade": "Anúncio de procedimento  n.º 25474/2025  -  Diário da República n.º 187/2025, Série II de 2025-09-29",
    "link": "https://diariodarepublica.pt/dr/detalhe/contrato-publico/25474-937017576"
  },
  {
    "numero_procedimento": "N/A",
    "entidade": "Anúncio de procedimento  n.º 25475/2025  -  Diário da República n.º 187/2025, Série II de 2025-09-29",
    "link": "https://diariodarepublica.pt/dr/detalhe/contrato-publico/25475-937017599"
  },
  {
    "numero_procedimento": "N/A",
    "entidade": "Anúncio de procedimento  n.º 25482/2025  -  Diário da República n.º 187/2025, Série II de 2025-09-29",
    "link": "https://diariodarepublica.pt/dr/detalhe/contrato-publico/25482-937017646"
  },
  {
    "numero_procedimento": "N/A",
    "entidade": "Anúncio de procedimento  n.º 25488/2025  -  Diário da República n.º 187/2025, Série II de 2025-09-29",
    "link": "https://diariodarepublica.pt/dr/detalhe/contrato-publico/25488-937049216"
  },
  {
    "numero_procedimento": "N/A",
    "entidade": "Anúncio de procedimento  n.º 25489/2025  -  Diário da República n.º 187/2025, Série II de 2025-09-29",
    "link": "https://diariodarepublica.pt/dr/detalhe/contrato-publico/25489-937049217"
  },
  {
    "numero_procedimento": "N/A",
    "entidade": "Anúncio de procedimento  n.º 25490/2025  -  Diário da República n.º 187/2025, Série II de 2025-09-29",
    "link": "https://diariodarepublica.pt/dr/detalhe/contrato-publico/25490-937049218"
  },
  {
    "numero_procedimento": "N/A",
    "entidade": "Anúncio de procedimento  n.º 25492/2025  -  Diário da República n.º 187/2025, Série II de 2025-09-29",
    "link": "https://diariodarepublica.pt/dr/detalhe/contrato-publico/25492-937049219"
  },
  {
    "numero_procedimento": "N/A",
    "entidade": "Anúncio de procedimento  n.º 25494/2025  -  Diário da República n.º 187/2025, Série II de 2025-09-29",
    "link": "https://diariodarepublica.pt/dr/detalhe/contrato-publico/25494-937049220"
  },
  {
    "numero_procedimento": "N/A",
    "entidade": "Anúncio de procedimento  n.º 25495/2025  -  Diário da República n.º 187/2025, Série II de 2025-09-29",
    "link": "https://diariodarepublica.pt/dr/detalhe/contrato-publico/25495-937049221"
  },
  {
    "numero_procedimento": "N/A",
    "entidade": "Anúncio de procedimento  n.º 25496/2025  -  Diário da República n.º 187/2025, Série II de 2025-09-29",
    "link": "https://diariodarepublica.pt/dr/detalhe/contrato-publico/25496-937049222"
  },
  {
    "numero_procedimento": "N/A",
    "entidade": "Anúncio de procedimento  n.º 25498/2025  -  Diário da República n.º 187/2025, Série II de 2025-09-29",
    "link": "https://diariodarepublica.pt/dr/detalhe/contrato-publico/25498-937049223"
  },
  {
    "numero_procedimento": "N/A",
    "entidade": "Anúncio de procedimento  n.º 25502/2025  -  Diário da República n.º 187/2025, Série II de 2025-09-29",
    "link": "https://diariodarepublica.pt/dr/detalhe/contrato-publico/25502-937049224"
  },
  {
    "numero_procedimento": "N/A",
    "entidade": "Anúncio de procedimento  n.º 25503/2025  -  Diário da República n.º 187/2025, Série II de 2025-09-29",
    "link": "https://diariodarepublica.pt/dr/detalhe/contrato-publico/25503-937049225"
  },
  {
    "numero_procedimento": "N/A",
    "entidade": "Anúncio de procedimento  n.º 25505/2025  -  Diário da República n.º 187/2025, Série II de 2025-09-29",
    "link": "https://diariodarepublica.pt/dr/detalhe/contrato-publico/25505-937049226"
  },
  {
    "numero_procedimento": "N/A",
    "entidade": "Anúncio de procedimento  n.º 25506/2025  -  Diário da República n.º 187/2025, Série II de 2025-09-29",
    "link": "https://diariodarepublica.pt/dr/detalhe/contrato-publico/25506-937049227"
  },
  {
    "numero_procedimento": "N/A",
    "entidade": "Anúncio de procedimento  n.º 25507/2025  -  Diário da República n.º 187/2025, Série II de 2025-09-29",
    "link": "https://diariodarepublica.pt/dr/detalhe/contrato-publico/25507-937049228"
  },
  {
    "numero_procedimento": "N/A",
    "entidade": "Anúncio de procedimento  n.º 25510/2025  -  Diário da República n.º 187/2025, Série II de 2025-09-29",
    "link": "https://diariodarepublica.pt/dr/detalhe/contrato-publico/25510-937049229"
  },
  {
    "numero_procedimento": "N/A",
    "entidade": "Anúncio de procedimento  n.º 25512/2025  -  Diário da República n.º 187/2025, Série II de 2025-09-29",
    "link": "https://diariodarepublica.pt/dr/detalhe/contrato-publico/25512-937049230"
  },
  {
    "numero_procedimento": "N/A",
    "entidade": "Anúncio de procedimento  n.º 25515/2025  -  Diário da República n.º 187/2025, Série II de 2025-09-29",
    "link": "https://diariodarepublica.pt/dr/detalhe/contrato-publico/25515-937049231"
  },
  {
    "numero_procedimento": "N/A",
    "entidade": "Anúncio de procedimento  n.º 25516/2025  -  Diário da República n.º 187/2025, Série II de 2025-09-29",
    "link": "https://diariodarepublica.pt/dr/detalhe/contrato-publico/25516-937049232"
  },
  {
    "numero_procedimento": "N/A",
    "entidade": "Anúncio de procedimento  n.º 25519/2025  -  Diário da República n.º 187/2025, Série II de 2025-09-29",
    "link": "https://diariodarepublica.pt/dr/detalhe/contrato-publico/25519-937049233"
  },
  {
    "numero_procedimento": "N/A",
    "entidade": "Anúncio de procedimento  n.º 25521/2025  -  Diário da República n.º 187/2025, Série II de 2025-09-29",
    "link": "https://diariodarepublica.pt/dr/detalhe/contrato-publico/25521-937049234"
  },
  {
    "numero_procedimento": "N/A",
    "entidade": "Anúncio de procedimento  n.º 25523/2025  -  Diário da República n.º 187/2025, Série II de 2025-09-29",
    "link": "https://diariodarepublica.pt/dr/detalhe/contrato-publico/25523-937049235"
  },
  {
    "numero_procedimento": "N/A",
    "entidade": "Anúncio de procedimento  n.º 25526/2025  -  Diário da República n.º 187/2025, Série II de 2025-09-29",
    "link": "https://diariodarepublica.pt/dr/detalhe/contrato-publico/25526-937049236"
  },
  {
    "numero_procedimento": "N/A",
    "entidade": "Anúncio de procedimento  n.º 25528/2025  -  Diário da República n.º 187/2025, Série II de 2025-09-29",
    "link": "https://diariodarepublica.pt/dr/detalhe/contrato-publico/25528-937049237"
  },
  {
    "numero_procedimento": "N/A",
    "entidade": "Anúncio de procedimento  n.º 25530/2025  -  Diário da República n.º 187/2025, Série II de 2025-09-29",
    "link": "https://diariodarepublica.pt/dr/detalhe/contrato-publico/25530-937049238"
  },
  {
    "numero_procedimento": "N/A",
    "entidade": "Anúncio de procedimento  n.º 25531/2025  -  Diário da República n.º 187/2025, Série II de 2025-09-29",
    "link": "https://diariodarepublica.pt/dr/detalhe/contrato-publico/25531-937049239"
  },
  {
    "numero_procedimento": "N/A",
    "entidade": "Anúncio de procedimento  n.º 25533/2025  -  Diário da República n.º 187/2025, Série II de 2025-09-29",
    "link": "https://diariodarepublica.pt/dr/detalhe/contrato-publico/25533-937049240"
  },
  {
    "numero_procedimento": "N/A",
    "entidade": "Anúncio de procedimento  n.º 25534/2025  -  Diário da República n.º 187/2025, Série II de 2025-09-29",
    "link": "https://diariodarepublica.pt/dr/detalhe/contrato-publico/25534-937049241"
  },
  {
    "numero_procedimento": "N/A",
    "entidade": "Anúncio de procedimento  n.º 25535/2025  -  Diário da República n.º 187/2025, Série II de 2025-09-29",
    "link": "https://diariodarepublica.pt/dr/detalhe/contrato-publico/25535-937049242"
  },
  {
    "numero_procedimento": "N/A",
    "entidade": "Anúncio de procedimento  n.º 25537/2025  -  Diário da República n.º 187/2025, Série II de 2025-09-29",
    "link": "https://diariodarepublica.pt/dr/detalhe/contrato-publico/25537-937049243"
  },
  {
    "numero_procedimento": "N/A",
    "entidade": "Anúncio de procedimento  n.º 25540/2025  -  Diário da República n.º 187/2025, Série II de 2025-09-29",
    "link": "https://diariodarepublica.pt/dr/detalhe/contrato-publico/25540-937049244"
  },
  {
    "numero_procedimento": "N/A",
    "entidade": "Anúncio de procedimento  n.º 25542/2025  -  Diário da República n.º 187/2025, Série II de 2025-09-29",
    "link": "https://diariodarepublica.pt/dr/detalhe/contrato-publico/25542-937049245"
  },
  {
    "numero_procedimento": "N/A",
    "entidade": "Anúncio de procedimento  n.º 25543/2025  -  Diário da República n.º 187/2025, Série II de 2025-09-29",
    "link": "https://diariodarepublica.pt/dr/detalhe/contrato-publico/25543-937049246"
  },
  {
    "numero_procedimento": "N/A",
    "entidade": "Anúncio de procedimento  n.º 25544/2025  -  Diário da República n.º 187/2025, Série II de 2025-09-29",
    "link": "https://diariodarepublica.pt/dr/detalhe/contrato-publico/25544-937049247"
  },
  {
    "numero_procedimento": "N/A",
    "entidade": "Anúncio de procedimento  n.º 25545/2025  -  Diário da República n.º 187/2025, Série II de 2025-09-29",
    "link": "https://diariodarepublica.pt/dr/detalhe/contrato-publico/25545-937049248"
  },
  {
    "numero_procedimento": "N/A",
    "entidade": "Anúncio de procedimento  n.º 25547/2025  -  Diário da República n.º 187/2025, Série II de 2025-09-29",
    "link": "https://diariodarepublica.pt/dr/detalhe/contrato-publico/25547-937049249"
  }
]