[
  {
    "numero_procedimento": "N/A",
    "entidade": "Anúncio de procedimento  n.º 23696/2025  -  Diário da República n.º 172/2025, Série II de 2025-09-08",
    "link": "https://diariodarepublica.pt/dr/detalhe/contrato-publico/23696-934420437"
  },
  {
    "numero_procedimento": "N/A",
    "entidade": "Anúncio de procedimento  n.º 23702/2025  -  Diário da República n.º 172/2025, Série II de 2025-09-08",
    "link": "https://diariodarepublica.pt/dr/detalhe/contrato-publico/23702-934420438"
  },
  {
    "numero_procedimento": "N/A",
    "entidade": "Anúncio de procedimento  n.º 23703/2025  -  Diário da República n.º 172/2025, Série II de 2025-09-08",
    "link": "https://diariodarepublica.pt/dr/detalhe/contrato-publico/23703-934420439"
  },
  {
    "numero_procedimento": "N/A",
    "entidade": "Anúncio de procedimento  n.º 23695/2025  -  Diário da República n.º 172/2025, Série II de 2025-09-08",
    "link": "https://diariodarepublica.pt/dr/detalhe/contrato-publico/23695-934422143"
  },
  {
    "numero_procedimento": "N/A",
    "entidade": "Anúncio de procedimento  n.º 23697/2025  -  Diário da República n.º 172/2025, Série II de 2025-09-08",
    "link": "https://diariodarepublica.pt/dr/detalhe/contrato-publico/23697-934422144"
  },
  {
    "numero_procedimento": "N/A",
    "entidade": "Anúncio de procedimento  n.º 23698/2025  -  Diário da República n.º 172/2025, Série II de 2025-09-08",
    "link": "https://diariodarepublica.pt/dr/detalhe/contrato-publico/23698-934422145"
  },
  {
    "numero_procedimento": "N/A",
    "entidade": "Anúncio de procedimento  n.º 23699/2025  -  Diário da República n.º 172/2025, Série II de 2025-09-08",
    "link": "https://diariodarepublica.pt/dr/detalhe/contrato-publico/23699-934454761"
  },
  {
    "numero_procedimento": "N/A",
    "entidade": "Anúncio de procedimento  n.º 23700/2025  -  Diário da República n.º 172/2025, Série II de 2025-09-08",
    "link": "https://diariodarepublica.pt/dr/detalhe/contrato-publico/23700-934454762"
  },
  {
    "numero_procedimento": "N/A",
    "entidade": "Anúncio de procedimento  n.º 23701/2025  -  Diário da República n.º 172/2025, Série II de 2025-09-08",
    "link": "https://diariodarepublica.pt/dr/detalhe/contrato-publico/23701-934454763"
  },
  {
    "numero_procedimento": "N/A",
    "entidade": "Anúncio de procedimento  n.º 23704/2025  -  Diário da República n.º 172/2025, Série II de 2025-09-08",
    "link": "https://diariodarepublica.pt/dr/detalhe/contrato-publico/23704-934454764"
  },
  {
    "numero_procedimento": "N/A",
    "entidade": "Anúncio de procedimento  n.º 23706/2025  -  Diário da República n.º 172/2025, Série II de 2025-09-08",
    "link": "https://diariodarepublica.pt/dr/detalhe/contrato-publico/23706-934454765"
  },
  {
    "numero_procedimento": "N/A",
    "entidade": "Anúncio de procedimento  n.º 23707/2025  -  Diário da República n.º 172/2025, Série II de 2025-09-08",
    "link": "https://diariodarepublica.pt/dr/detalhe/contrato-publico/23707-934454766"
  },
  {
    "numero_procedimento": "N/A",
    "entidade": "Anúncio de procedimento  n.º 23708/2025  -  Diário da República n.º 172/2025, Série II de 2025-09-08",
    "link": "https://diariodarepublica.pt/dr/detalhe/contrato-publico/23708-934454767"
  },
  {
    "numero_procedimento": "N/A",
    "entidade": "Anúncio de procedimento  n.º 23710/2025  -  Diário da República n.º 172/2025, Série II de 2025-09-08",
    "link": "https://diariodarepublica.pt/dr/detalhe/contrato-publico/23710-934454768"
  },
  {
    "numero_procedimento": "N/A",
    "entidade": "Anúncio de procedimento  n.º 23715/2025  -  Diário da República n.º 172/2025, Série II de 2025-09-08",
    "link": "https://diariodarepublica.pt/dr/detalhe/contrato-publico/23715-934454769"
  },
  {
    "numero_procedimento": "N/A",
    "entidade": "Anúncio de procedimento  n.º 23717/2025  -  Diário da República n.º 172/2025, Série II de 2025-09-08",
    "link": "https://diariodarepublica.pt/dr/detalhe/contrato-publico/23717-934454770"
  },
  {
    "numero_procedimento": "N/A",
    "entidade": "Anúncio de procedimento  n.º 23719/2025  -  Diário da República n.º 172/2025, Série II de 2025-09-08",
    "link": "https://diariodarepublica.pt/dr/detalhe/contrato-publico/23719-934454771"
  },
  {
    "numero_procedimento": "N/A",
    "entidade": "Anúncio de procedimento  n.º 23721/2025  -  Diário da República n.º 172/2025, Série II de 2025-09-08",
    "link": "https://diariodarepublica.pt/dr/detalhe/contrato-publico/23721-934454772"
  },
  {
    "numero_procedimento": "N/A",
    "entidade": "Anúncio de procedimento  n.º 23722/2025  -  Diário da República n.º 172/2025, Série II de 2025-09-08",
    "link": "https://diariodarepublica.pt/dr/detalhe/contrato-publico/23722-934454773"
  },
  {
    "numero_procedimento": "N/A",
    "entidade": "Anúncio de procedimento  n.º 23723/2025  -  Diário da República n.º 172/2025, Série II de 2025-09-08",
    "link": "https://diariodarepublica.pt/dr/detalhe/contrato-publico/23723-934454774"
  },
  {
    "numero_procedimento": "N/A",
    "entidade": "Anúncio de procedimento  n.º 23705/2025  -  Diário da República n.º 172/2025, Série II de 2025-09-08",
    "link": "https://diariodarepublica.pt/dr/detalhe/contrato-publico/23705-934464551"
  },
  {
    "numero_procedimento": "N/A",
    "entidade": "Anúncio de procedimento  n.º 23709/2025  -  Diário da República n.º 172/2025, Série II de 2025-09-08",
    "link": "https://diariodarepublica.pt/dr/detalhe/contrato-publico/23709-934464552"
  },
  {
    "numero_procedimento": "N/A",
    "entidade": "Anúncio de procedimento  n.º 23711/2025  -  Diário da República n.º 172/2025, Série II de 2025-09-08",
    "link": "https://diariodarepublica.pt/dr/detalhe/contrato-publico/23711-934464553"
  },
  {
    "numero_procedimento": "N/A",
    "entidade": "Anúncio de procedimento  n.º 23712/2025  -  Diário da República n.º 172/2025, Série II de 2025-09-08",
    "link": "https://diariodarepublica.pt/dr/detalhe/contrato-publico/23712-934464554"
  },
  {
    "numero_procedimento": "N/A",
    "entidade": "Anúncio de procedimento  n.º 23713/2025  -  Diário da República n.º 172/2025, Série II de 2025-09-08",
    "link": "https://diariodarepublica.pt/dr/detalhe/contrato-publico/23713-934464555"
  },
  {
    "numero_procedimento": "N/A",
    "entidade": "Anúncio de procedimento  n.º 23714/2025  -  Diário da República n.º 172/2025, Série II de 2025-09-08",
    "link": "https://diariodarepublica.pt/dr/detalhe/contrato-publico/23714-934464556"
  },
  {
    "numero_procedimento": "N/A",
    "entidade": "Anúncio de procedimento  n.º 23716/2025  -  Diário da República n.º 172/2025, Série II de 2025-09-08",
    "link": "https://diariodarepublica.pt/dr/detalhe/contrato-publico/23716-934464557"
  },
  {
    "numero_procedimento": "N/A",
    "entidade": "Anúncio de procedimento  n.º 23718/2025  -  Diário da República n.º 172/2025, Série II de 2025-09-08",
    "link": "https://diariodarepublica.pt/dr/detalhe/contrato-publico/23718-934464558"
  },
  {
    "numero_procedimento": "N/A",
    "entidade": "Anúncio de procedimento  n.º 23720/2025  -  Diário da República n.º 172/2025, Série II de 2025-09-08",
    "link": "https://diariodarepublica.pt/dr/detalhe/contrato-publico/23720-934464559"
  },
  {
    "numero_procedimento": "N/A",
    "entidade": "Anúncio de procedimento  n.º 23724/2025  -  Diário da República n.º 172/2025, Série II de 2025-09-08",
    "link": "https://diariodarepublica.pt/dr/detalhe/contrato-publico/23724-934464560"
  },
  {
    "numero_procedimento": "N/A",
    "entidade": "Anúncio de procedimento  n.º 23725/2025  -  Diário da República n.º 172/2025, Série II de 2025-09-08",
    "link": "https://diariodarepublica.pt/dr/detalhe/contrato-publico/23725-934464561"
  },
  {
    "numero_procedimento": "N/A",
    "entidade": "Anúncio de procedimento  n.º 23727/2025  -  Diário da República n.º 172/2025, Série II de 2025-09-08",
    "link": "https://diariodarepublica.pt/dr/detalhe/contrato-publico/23727-934464562"
  },
  {
    "numero_procedimento": "N/A",
    "entidade": "Anúncio de procedimento  n.º 23732/2025  -  Diário da República n.º 172/2025, Série II de 2025-09-08",
    "link": "https://diariodarepublica.pt/dr/detalhe/contrato-publico/23732-934464563"
  },
  {
    "numero_procedimento": "N/A",
    "entidade": "Anúncio de procedimento  n.º 23733/2025  -  Diário da República n.º 172/2025, Série II de 2025-09-08",
    "link": "https://diariodarepublica.pt/dr/detalhe/contrato-publico/23733-934464564"
  },
  {
    "numero_procedimento": "N/A",
    "entidade": "Anúncio de procedimento  n.º 23734/2025  -  Diário da República n.º 172/2025, Série II de 2025-09-08",
    "link": "https://diariodarepublica.pt/dr/detalhe/contrato-publico/23734-934464565"
  },
  {
    "numero_procedimento": "N/A",
    "entidade": "Anúncio de procedimento  n.º 23735/2025  -  Diário da República n.º 172/2025, Série II de 2025-09-08",
    "link": "https://diariodarepublica.pt/dr/detalhe/contrato-publico/23735-934464566"
  },
  {
    "numero_procedimento": "N/A",
    "entidade": "Anúncio de procedimento  n.º 23742/2025  -  Diário da República n.º 172/2025, Série II de 2025-09-08",
    "link": "https://diariodarepublica.pt/dr/detalhe/contrato-publico/23742-934464567"
  },
  {
    "numero_procedimento": "N/A",
    "entidade": "Anúncio de procedimento  n.º 23744/2025  -  Diário da República n.º 172/2025, Série II de 2025-09-08",
    "link": "https://diariodarepublica.pt/dr/detalhe/contrato-publico/23744-934464568"
  },
  {
    "numero_procedimento": "N/A",
    "entidade": "Anúncio de procedimento  n.º 23745/2025  -  Diário da República n.º 172/2025, Série II de 2025-09-08",
    "link": "https://diariodarepublica.pt/dr/detalhe/contrato-publico/23745-934464569"
  },
  {
    "numero_procedimento": "N/A",
    "entidade": "Anúncio de procedimento  n.º 23746/2025  -  Diário da República n.º 172/2025, Série II de 2025-09-08",
    "link": "https://diariodarepublica.pt/dr/detalhe/contrato-publico/23746-934464570"
  },
  {
    "numero_procedimento": "N/A",
    "entidade": "Anúncio de procedimento  n.º 23747/2025  -  Diário da República n.º 172/2025, Série II de 2025-09-08",
    "link": "https://diariodarepublica.pt/dr/detalhe/contrato-publico/23747-934464571"
  },
  {
    "numero_procedimento": "N/A",
    "entidade": "Anúncio de procedimento  n.º 23748/2025  -  Diário da República n.º 172/2025, Série II de 2025-09-08",
    "link": "https://diariodarepublica.pt/dr/detalhe/contrato-publico/23748-934464572"
  },
  {
    "numero_procedimento": "N/A",
    "entidade": "Anúncio de procedimento  n.º 23749/2025  -  Diário da República n.º 172/2025, Série II de 2025-09-08",
    "link": "https://diariodarepublica.pt/dr/detalhe/contrato-publico/23749-934464573"
  },
  {
    "numero_procedimento": "N/A",
    "entidade": "Anúncio de procedimento  n.º 23726/2025  -  Diário da República n.º 172/2025, Série II de 2025-09-08",
    "link": "https://diariodarepublica.pt/dr/detalhe/contrato-publico/23726-934465375"
  },
  {
    "numero_procedimento": "N/A",
    "entidade": "Anúncio de procedimento  n.º 23728/2025  -  Diário da República n.º 172/2025, Série II de 2025-09-08",
    "link": "https://diariodarepublica.pt/dr/detalhe/contrato-publico/23728-934465376"
  },
  {
    "numero_procedimento": "N/A",
    "entidade": "Anúncio de procedimento  n.º 23729/2025  -  Diário da República n.º 172/2025, Série II de 2025-09-08",
    "link": "https://diariodarepublica.pt/dr/detalhe/contrato-publico/23729-934465377"
  },
  {
    "numero_procedimento": "N/A",
    "entidade": "Anúncio de procedimento  n.º 23730/2025  -  Diário da República n.º 172/2025, Série II de 2025-09-08",
    "link": "https://diariodarepublica.pt/dr/detalhe/contrato-publico/23730-934465378"
  },
  {
    "numero_procedimento": "N/A",
    "entidade": "Anúncio de procedimento  n.º 23731/2025  -  Diário da República n.º 172/2025, Série II de 2025-09-08",
    "link": "https://diariodarepublica.pt/dr/detalhe/contrato-publico/23731-934465379"
  },
  {
    "numero_procedimento": "N/A",
    "entidade": "Anúncio de procedimento  n.º 23736/2025  -  Diário da República n.º 172/2025, Série II de 2025-09-08",
    "link": "https://diariodarepublica.pt/dr/detalhe/contrato-publico/23736-934465380"
  },
  {
    "numero_procedimento": "N/A",
    "entidade": "Anúncio de procedimento  n.º 23737/2025  -  Diário da República n.º 172/2025, Série II de 2025-09-08",
    "link": "https://diariodarepublica.pt/dr/detalhe/contrato-publico/23737-934465381"
  },
  {
    "numero_procedimento": "N/A",
    "entidade": "Anúncio de procedimento  n.º 23738/2025  -  Diário da República n.º 172/2025, Série II de 2025-09-08",
    "link": "https://diariodarepublica.pt/dr/detalhe/contrato-publico/23738-934465382"
  },
  {
    "numero_procedimento": "N/A",
    "entidade": "Anúncio de procedimento  n.º 23739/2025  -  Diário da República n.º 172/2025, Série II de 2025-09-08",
    "link": "https://diariodarepublica.pt/dr/detalhe/contrato-publico/23739-934465383"
  },
  {
    "numero_procedimento": "N/A",
    "entidade": "Anúncio de procedimento  n.º 23740/2025  -  Diário da República n.º 172/2025, Série II de 2025-09-08",
    "link": "https://diariodarepublica.pt/dr/detalhe/contrato-publico/23740-934465384"
  },
  {
    "numero_procedimento": "N/A",
    "entidade": "Anúncio de procedimento  n.º 23741/2025  -  Diário da República n.º 172/2025, Série II de 2025-09-08",
    "link": "https://diariodarepublica.pt/dr/detalhe/contrato-publico/23741-934465385"
  },
  {
    "numero_procedimento": "N/A",
    "entidade": "Anúncio de procedimento  n.º 23743/2025  -  Diário da República n.º 172/2025, Série II de 2025-09-08",
    "link": "https://diariodarepublica.pt/dr/detalhe/contrato-publico/23743-934465386"
  }
]